deltastudio/__init__.py
deltastudio/auth.py
deltastudio/config.py
deltastudio/core.py
deltastudio/helpers.py
deltastudio/quality/__init__.py
deltastudio/quality/basics.py
deltastudio/quality/checks.py
deltastudio/sources/__init__.py
deltastudio/sources/csv.py
deltastudio/sources/delta.py
deltastudio/sources/mssql.py
deltastudio/sources/parquet.py
deltastudio-2.0.dist-info/LICENSE
deltastudio-2.0.dist-info/METADATA
deltastudio-2.0.dist-info/WHEEL
deltastudio-2.0.dist-info/top_level.txt
deltastudio-2.0.dist-info/RECORD
