Metadata-Version: 2.1
Name: deltastudio
Version: 2.0
Summary: A package to simpify working with Delta Lake OSS.
Author: Morteza Hajipour
Author-email: mortezahajipour.works@gmail.com
License-File: LICENSE
